README.md
setup.py
pyes_cel/__init__.py
pyes_cel/cel.py
pyes_cel.egg-info/PKG-INFO
pyes_cel.egg-info/SOURCES.txt
pyes_cel.egg-info/dependency_links.txt
pyes_cel.egg-info/top_level.txt