Metadata-Version: 1.0
Name: pyes-cel
Version: 1.0.0
Summary: Convert CEL To DSL
Home-page: https://github.com/secoba/pyes_cel
Author: lynn
Author-email: lynn@sstsec.com
License: MIT Licence
Keywords: pip,pycel
Platform: any
